{
  "entityType" : "REPORT_TEMPLATE",
  "entity" : {
    "configuration" : {
      "format" : "PDF",
      "components" : [ {
        "background" : null,
        "borderColor" : null,
        "borderRadius" : null,
        "borderWidth" : null,
        "dataSources" : [ ],
        "margins" : null,
        "paddings" : null,
        "subType" : null,
        "type" : "RICH_TEXT",
        "value" : "<p style=\"line-height: 1.5;\">Lorem ipsum dolor sit amet, consectetur adipiscing elit. Donec libero orci, faucibus in iaculis quis, vestibulum sit amet ligula. Nulla facilisi. Ut ut iaculis tortor.</p>"
      }, {
        "background" : null,
        "borderColor" : null,
        "borderRadius" : null,
        "borderWidth" : null,
        "dataSources" : [ {
          "alarmFilterConfig" : {
            "assigneeId" : null,
            "searchPropagatedAlarms" : false,
            "severityList" : null,
            "statusList" : [ "ACTIVE" ],
            "typeList" : null
          },
          "dataKeys" : [ {
            "aggregationType" : null,
            "color" : null,
            "decimals" : 0,
            "label" : "Temperature",
            "name" : "temperature",
            "postFuncBody" : null,
            "settings" : null,
            "timewindow" : null,
            "type" : "timeseries",
            "units" : "°C",
            "usePostProcessing" : false
          } ],
          "deviceId" : "aac5bb20-84ce-11f0-9dcf-813811befd2b",
          "entityAliasId" : null,
          "filterId" : null,
          "latestDataKeys" : [ ],
          "type" : "device"
        } ],
        "margins" : {
          "bottom" : 0,
          "left" : 0,
          "right" : 0,
          "top" : 20
        },
        "paddings" : null,
        "showTableHeading" : true,
        "showTimestamp" : true,
        "subType" : null,
        "tableHeading" : {
          "color" : "#000",
          "font" : {
            "family" : "Roboto",
            "size" : 20.0,
            "style" : "normal",
            "weight" : "normal"
          },
          "height" : 40,
          "text" : "${entityName}",
          "textAlignment" : "center",
          "verticalAlignment" : "middle"
        },
        "tableSortOrder" : {
          "column" : "Timestamp",
          "direction" : "DESC"
        },
        "timestampColumnSettings" : {
          "cell" : null,
          "columnWidth" : null,
          "header" : null,
          "type" : "COLUMN"
        },
        "timestampLabel" : "Timestamp",
        "timestampPattern" : "yyyy-MM-dd HH:mm:ss",
        "timewindow" : {
          "aggregation" : {
            "limit" : 200,
            "type" : "NONE"
          },
          "history" : {
            "historyType" : 0,
            "interval" : 1000,
            "timewindowMs" : 86400000
          },
          "timezone" : null
        },
        "type" : "TIME_SERIES_TABLE"
      }, {
        "alignment" : "center",
        "background" : null,
        "borderColor" : null,
        "borderRadius" : null,
        "borderWidth" : null,
        "config" : {
          "baseUrl" : "https://thingsboard.cloud",
          "dashboardId" : "e5511fd0-21f1-11f1-93d4-a32bb61f9d35",
          "namePattern" : null,
          "state" : "",
          "timewindow" : {
            "selectedTab" : 1,
            "history" : {
              "historyType" : 0,
              "interval" : 1000,
              "timewindowMs" : 86400000
            }
          },
          "timezone" : "Europe/Kiev",
          "type" : "png",
          "useCurrentUserCredentials" : false,
          "useDashboardTimewindow" : true,
          "userId" : null
        },
        "customWidth" : 100,
        "dataSources" : [ {
          "alarmFilterConfig" : null,
          "dataKeys" : [ ],
          "deviceId" : null,
          "entityAliasId" : null,
          "filterId" : null,
          "latestDataKeys" : null,
          "type" : "entity"
        } ],
        "margins" : null,
        "paddings" : null,
        "subType" : null,
        "type" : "DASHBOARD",
        "widthType" : "fitWidth"
      } ],
      "entityAliases" : [ ],
      "filters" : [ ],
      "footer" : {
        "components" : [ ],
        "enabled" : true,
        "firstPage" : {
          "components" : [ ],
          "enabled" : false,
          "firstPage" : null
        }
      },
      "format" : "PDF",
      "header" : {
        "components" : [ {
          "background" : null,
          "borderColor" : null,
          "borderRadius" : null,
          "borderWidth" : null,
          "color" : "#000",
          "dataSources" : [ ],
          "font" : {
            "family" : "Roboto",
            "size" : 40.0,
            "style" : "normal",
            "weight" : "normal"
          },
          "height" : null,
          "margins" : null,
          "paddings" : null,
          "subType" : null,
          "textAlignment" : "center",
          "type" : "HEADING",
          "value" : "Heading",
          "verticalAlignment" : "middle"
        } ],
        "enabled" : true,
        "firstPage" : {
          "components" : [ ],
          "enabled" : false,
          "firstPage" : null
        }
      },
      "namePattern" : "report-%d{yyyy-MM-dd_HH:mm:ss}",
      "pageBackground" : "#fff",
      "pageMargins" : {
        "bottom" : 20,
        "left" : 20,
        "right" : 20,
        "top" : 20
      },
      "pageOrientation" : "PORTRAIT",
      "pageSize" : "A4",
      "timeDataPattern" : "yyyy-MM-dd HH:mm:ss"
    },
    "customerId" : {
      "entityType" : "CUSTOMER",
      "id" : "13814000-1dd2-11b2-8080-808080808080"
    },
    "description" : null,
    "externalId" : null,
    "format" : "PDF",
    "id" : {
      "entityType" : "REPORT_TEMPLATE",
      "id" : "7b2190a0-2c27-11f1-9c6f-b71bb2771567"
    },
    "name" : "template",
    "ownerId" : null,
    "type" : "REPORT"
  }
}